milkcow/__init__.py
milkcow/main.py
milkcow/util.py
milkcow/cli/__init__.py
milkcow/cli/command_line.py
milkcow/common/__init__.py
milkcow/common/basebufferedsocket.py
milkcow/common/basecacheddb.py
milkcow/common/basedb.py
milkcow/common/basestore.py
milkcow/common/transcode.py
milkcow/core/__init__.py
milkcow/core/basebufferedsocket.py
milkcow/core/classes.py
milkcow/core/connections.py
milkcow/core/senders.py
milkcow/core/milkcat/__init__.py
milkcow/core/milkcat/milkcat.py
milkcow/run/__init__.py
milkcow/run/command_line.py
milkcow/test/__init__.py
milkcow/test/example/__init__.py
milkcow/test/example/ex1.py
milkcow/test/example/jc_ex.py
milkcow/test/example/mc_ex.py
milkcow/test/example/my_model_class.py
milkcow/test/example/oc_ex.py
milkcow/util/__init__.py
milkcow/util/cli.py
run/__init__.py
run/command_line.py
milkcow-0.0.11.dist-info/LICENSE.txt
milkcow-0.0.11.dist-info/METADATA
milkcow-0.0.11.dist-info/WHEEL
milkcow-0.0.11.dist-info/entry_points.txt
milkcow-0.0.11.dist-info/top_level.txt
milkcow-0.0.11.dist-info/RECORD
