Metadata-Version: 2.1
Name: milkcow
Version: 0.0.11
Summary: A library pulling json into python projects
Home-page: https://github.com/SamReynoso/milkcow
Author: SamReynoso
License: MIT
Classifier: Development Status :: 2 - Pre-Alpha
Classifier: Intended Audience :: Developers
Classifier: Intended Audience :: System Administrators
Classifier: License :: OSI Approved :: MIT License
Classifier: Programming Language :: Python
License-File: LICENSE.txt
